README.md
bounds.py
setup.py
bounds.egg-info/PKG-INFO
bounds.egg-info/SOURCES.txt
bounds.egg-info/dependency_links.txt
bounds.egg-info/requires.txt
bounds.egg-info/top_level.txt